toolbox_maker/__init__.py
toolbox_maker/functions.py
toolbox_maker-1.0.0.dist-info/LICENSE
toolbox_maker-1.0.0.dist-info/METADATA
toolbox_maker-1.0.0.dist-info/WHEEL
toolbox_maker-1.0.0.dist-info/top_level.txt
toolbox_maker-1.0.0.dist-info/RECORD
